ezdmb/__init__.py
ezdmb/__main__.py
ezdmb/Controller/Configuration.py
ezdmb/Controller/Configuration_test.py
ezdmb/Controller/LoggingUtility.py
ezdmb/Controller/LoggingUtility_test.py
ezdmb/Controller/__init__.py
ezdmb/Resources/__init__.py
ezdmb/Utility/ShortcutUtility.py
ezdmb/Utility/__init__.py
ezdmb/View/AboutDialog.py
ezdmb/View/ConfigDialog.py
ezdmb/View/FullScreenWindow.py
ezdmb/View/MenuContentViewUtility.py
ezdmb/View/MenuContentViewUtility_test.py
ezdmb/View/PreviewWindow.py
ezdmb/View/__init__.py
ezdmb-0.9.45.dist-info/licenses/LICENSE
ezdmb-0.9.45.dist-info/METADATA
ezdmb-0.9.45.dist-info/WHEEL
ezdmb-0.9.45.dist-info/entry_points.txt
ezdmb-0.9.45.dist-info/top_level.txt
ezdmb-0.9.45.dist-info/RECORD
