Metadata-Version: 2.4
Name: ezdmb
Version: 0.9.45
Summary: A dead-simple digital menu board configurator and display.
Home-page: https://github.com/justinmichaelvieira/ezdmb
Author: Justin Vieira
Author-email: justin@rancorsoft.com
License: LGPL-3.0-only
Project-URL: Bug Tracker, https://github.com/mahesh-maximus/helloworld-pyp/issues
Classifier: Programming Language :: Python :: 3
Requires-Python: >=3.4
License-File: LICENSE
Requires-Dist: PyQt5>=5.15.2
Requires-Dist: pyqt_distutils
Requires-Dist: black
Requires-Dist: aqtinstall
Requires-Dist: pyinstaller
Dynamic: author
Dynamic: author-email
Dynamic: classifier
Dynamic: description
Dynamic: description-content-type
Dynamic: home-page
Dynamic: license
Dynamic: license-file
Dynamic: project-url
Dynamic: requires-dist
Dynamic: requires-python
Dynamic: summary
